setup.py
mworks/__init__.py
mworks/sysplorer/__init__.py
mworks/sysplorer/auto_generate_md_documents.py
mworks/sysplorer/config.ini
mworks/sysplorer/mw_ani_listener.py
mworks/sysplorer/mw_class.py
mworks/sysplorer/start_sysplorer.py
mworks/sysplorer/sysplorer_api.py
mworks/sysplorer/DesignOptExp/DesignOptExp.py
mworks/sysplorer/DesignOptExp/__init__.py
mworks/sysplorer/DesignOptExpGui/DesignOptExpGui.py
mworks/sysplorer/DesignOptExpGui/__init__.py
mworks/sysplorer/DesignOptMpe/DesignOptMpe.py
mworks/sysplorer/DesignOptMpe/__init__.py
mworks/sysplorer/DesignOptMro/DesignOptMro.py
mworks/sysplorer/DesignOptMro/__init__.py
mworks/sysplorer/DesignOptPsa/DesignOptPsa.py
mworks/sysplorer/DesignOptPsa/__init__.py
mworks/sysplorer/HILExport/HILExport.py
mworks/sysplorer/HILExport/__init__.py
mworks/sysplorer/LinearEsitmate/__init__.py
mworks/sysplorer/LinearEsitmate/linear_esitmate.py
mworks/sysplorer/MwAppOptions/MwAppOptions.py
mworks/sysplorer/MwAppOptions/__init__.py
mworks/sysplorer/MwCmdWindow/MwCmdWindow.py
mworks/sysplorer/MwCmdWindow/__init__.py
mworks/sysplorer/ROMBuilder/ROMPlugin.py
mworks/sysplorer/ROMBuilder/__init__.py
mworks/sysplorer/SimulinkImporter/SimulinkImporter.py
mworks/sysplorer/SimulinkImporter/__init__.py
mworks/sysplorer/TextViewPlugin/__init__.py
mworks/sysplorer/TextViewPlugin/text_view_plugin.py
mworks/sysplorer/Utils/__init__.py
mworks/sysplorer/Utils/decorator.py
mworks/sysplorer/Utils/mw_connect.py
mworks/sysplorer/Utils/os_utils.py
mworks_sysplorer.egg-info/PKG-INFO
mworks_sysplorer.egg-info/SOURCES.txt
mworks_sysplorer.egg-info/dependency_links.txt
mworks_sysplorer.egg-info/entry_points.txt
mworks_sysplorer.egg-info/requires.txt
mworks_sysplorer.egg-info/top_level.txt