Metadata-Version: 2.4
Name: mworks_sysplorer
Version: 2.0.8
Summary: This is a Sysplorer API by Tong Yuan.
Author: lipy@TongYuan
Author-email: lipy@tongyuan.cc
Requires-Python: >=3.7,<3.12
Requires-Dist: websocket-client
Requires-Dist: jsonrpcclient
Requires-Dist: colorama
Requires-Dist: psutil
Dynamic: author
Dynamic: author-email
Dynamic: requires-dist
Dynamic: requires-python
Dynamic: summary
